odoo/addons/mrp_production_quant_manual_assign/README.rst
odoo/addons/mrp_production_quant_manual_assign/__init__.py
odoo/addons/mrp_production_quant_manual_assign/__manifest__.py
odoo/addons/mrp_production_quant_manual_assign/i18n/es.po
odoo/addons/mrp_production_quant_manual_assign/i18n/fr.po
odoo/addons/mrp_production_quant_manual_assign/i18n/hr.po
odoo/addons/mrp_production_quant_manual_assign/i18n/it.po
odoo/addons/mrp_production_quant_manual_assign/i18n/ja.po
odoo/addons/mrp_production_quant_manual_assign/i18n/mrp_production_quant_manual_assign.pot
odoo/addons/mrp_production_quant_manual_assign/i18n/pt_BR.po
odoo/addons/mrp_production_quant_manual_assign/models/__init__.py
odoo/addons/mrp_production_quant_manual_assign/models/mrp_bom.py
odoo/addons/mrp_production_quant_manual_assign/models/stock_move.py
odoo/addons/mrp_production_quant_manual_assign/readme/CONTRIBUTORS.md
odoo/addons/mrp_production_quant_manual_assign/readme/DESCRIPTION.md
odoo/addons/mrp_production_quant_manual_assign/readme/USAGE.md
odoo/addons/mrp_production_quant_manual_assign/static/description/icon.png
odoo/addons/mrp_production_quant_manual_assign/static/description/index.html
odoo/addons/mrp_production_quant_manual_assign/tests/__init__.py
odoo/addons/mrp_production_quant_manual_assign/tests/test_mrp_production_quant_manual_assign.py
odoo/addons/mrp_production_quant_manual_assign/views/mrp_production_views.xml
odoo/addons/mrp_production_quant_manual_assign/wizards/__init__.py
odoo/addons/mrp_production_quant_manual_assign/wizards/assign_manual_quants.py
odoo/addons/mrp_production_quant_manual_assign/wizards/assign_manual_quants_view.xml
odoo_addon_mrp_production_quant_manual_assign-17.0.1.0.1.3.dist-info/METADATA
odoo_addon_mrp_production_quant_manual_assign-17.0.1.0.1.3.dist-info/WHEEL
odoo_addon_mrp_production_quant_manual_assign-17.0.1.0.1.3.dist-info/top_level.txt
odoo_addon_mrp_production_quant_manual_assign-17.0.1.0.1.3.dist-info/RECORD
