Metadata-Version: 2.1
Name: odoo-addon-mrp_production_quant_manual_assign
Version: 17.0.1.0.1.3
Requires-Python: >=3.10
Requires-Dist: odoo-addon-stock_quant_manual_assign>=17.0dev,<17.1dev
Requires-Dist: odoo>=17.0a,<17.1dev
Summary: Production - Manual Quant Assignment
Home-page: https://github.com/OCA/manufacture
License: AGPL-3
Author: Quartile Limited, ForgeFlow, Odoo Community Association (OCA)
Author-email: support@odoo-community.org
Classifier: Programming Language :: Python
Classifier: Framework :: Odoo
Classifier: Framework :: Odoo :: 17.0
Classifier: License :: OSI Approved :: GNU Affero General Public License v3
